{
  "data": {
    "orderHistoryForSalesRepV2": {
      "OrderCount": 1,
      "OrderHistory": [
        {
          "OrderBasicInformation": {
            "SoldTo": "0030068160",
            "CompanyName": "DR SHAMIR CHANDRAN",
            "ShipTo": "0070132214",
            "PaymentTerm": {
              "PaymentTermCode": "",
              "PaymentTermDescription": ""
            }
          },
          "OrderItems": [
            {
              "MaterialCode": "000000000023063780",
              "MaterialDescription": "(M) TEOSYAL PS ULTIM 3ML PRFS 1'S",
              "CreatedTime": "141839",
              "CreatedDate": "20230613",
              "Qty": 2,
              "UnitPrice": 1320,
              "TotalPrice": 2640,
              "Status": "Pending release - credit check",
              "LineNumber": "000010",
              "Tax": 0,
              "DeliveryDate": "20230613",
              "DeliveryTime": "",
              "OrderType": "ZPOR",
              "EZRXNumber": "EZRX-9e028e9",
              "OrderNumber": "0200220305",
              "OrderBy": "testintsalesrep",
              "PurchaseOrderType": "EZC",
              "WarehouseStorageCondition": "",
              "Available": true,
              "Batch": "+L-134005C",
              "ExpiryDate": "20251031",
              "IsMarketplace": false,
              "Seller": "",
              "POReference": "",
              "ManufactureName": "",
              "InvoiceNumber": "0100000",
              "TelephoneNumber": "014-6894547"
            }
          ]
        }
      ]
    }
  },
  "extensions": {
    "trace-id": "f1ae101a72aac3daf390c9b0a94011e7"
  }
}