{
    "data": {
        "orderHistory": {
            "orderCount": 2,
            "creatingOrderIds": [],
            "orderHeaders": [
                {
                    "Type": "ZPOR",
                    "OrderNumber": "0200221035",
                    "EZRXNumber": "EZRX-d6a0c46",
                    "SoldTo": "0000100208",
                    "ShipTo": "0000100208",
                    "CompanyName": "BAXTER HEALTHCARE (MALAYSIA) SDN BHD",
                    "OrderValue": 3000,
                    "ProcessingStatus": "Order Pending",
                    "CreatedDate": "20230613",
                    "CreatedTime": "15:52:30",
                    "RequestedDeliveryDate": "20230613",
                    "TotalTax": 0,
                    "POReference": "",
                    "MaterialCount": 1,
                    "ItmDescription": "TRI TS PLUS INSERT X3 POLY#1  11MM",
                    "HasPOAttachment": false,
                    "ItmCount": 2,
                    "TelephoneNumber": "",
                    "OrderBy": "rootadmin"
                },
                {
                    "Type": "ZPOR",
                    "OrderNumber": "0200220257",
                    "EZRXNumber": "EZRX-2502d64",
                    "SoldTo": "0000100208",
                    "ShipTo": "0000100208",
                    "CompanyName": "BAXTER HEALTHCARE (MALAYSIA) SDN BHD",
                    "OrderValue": 9000,
                    "ProcessingStatus": "Order Cancelled",
                    "CreatedDate": "20230613",
                    "CreatedTime": "15:51:07",
                    "RequestedDeliveryDate": "20230613",
                    "TotalTax": 0,
                    "POReference": "",
                    "MaterialCount": 1,
                    "ItmDescription": "TRI TS PLUS INSERT X3 POLY#1  11MM",
                    "HasPOAttachment": false,
                    "ItmCount": 6,
                    "TelephoneNumber": "",
                    "OrderBy": "rootadmin"
                }
            ]
        }
    },
    "extensions": {
        "trace-id": "f85f05ad9d064ff44e7afb745dead67b"
    }
}