{
    "data": {
      "requestInformationV2": {
        "requestHeader": {
          "soldTo": "0030032223",
          "shipTo": "0070042688",
          "createdBy": "ezrxtest05",
          "returnType": "500",
          "status": "PENDING",
          "createdDate": "20230127",
          "createdTime": "1674804573",
          "requestID": "EZRE-260123000411",
          "salesOrg": "2601",
          "refundTotal": "31.58",
          "totalItemCount": "1",
          "returnInvoices": [],
          "salesDoc": [],
          "returnTypeDesc": "Return",
          "ppaHeld": true,
          "cName1": "Lazada Singapore Pte Ltd",
          "cName2": "",
          "cName3": "",
          "cName4": "",
          "street1": "8 Shenton Way",
          "street2": "#43-01 AXA Tower",
          "street3": "",
          "street4": "",
          "__typename": "requestHeader"
        },
        "requestInformationV2": [
          {
            "invoiceNo": "1080004879",
            "returnValue": "31.580000",
            "actionRequired": [],
            "expiryDate": "20260519",
            "comment": "",
            "salesDocument": "0200127913",
            "exchangeOrder": "",
            "refundCurrency": "SGD",
            "rejectReason": "",
            "exchangeOrderNumber": "0060153327",
            "docType": "ZPRE",
            "referenceDocument": "",
            "division": "00",
            "purchaseMethod": "DSS",
            "usage": "",
            "distributionChannel": "10",
            "approvalTimeStamp": "1674804573",
            "createdTimeStamp": "",
            "poDate": "2021-10-28",
            "returnQuantity": "1",
            "unitPrice": "31.580000",
            "totalPrice": "31.580000",
            "billingItemNumber": "000020",
            "salesDocumentItemNumber": "000020",
            "materialNumber": "000000000021026761",
            "materialDescription": "Physiogel DMT Body Lotion 200ml",
            "batch": "2190PG",
            "materialGroup": "ZCH",
            "imageUrl": [],
            "attachmentUrl": [],
            "plant": "2617",
            "storageLocation": "1001",
            "highLevelItemCode": "",
            "orderReason": "",
            "priceDate": "20211108",
            "createdDate": "20230127",
            "overrideType": "",
            "overrideValue": "",
            "returnOrderText": "T46",
            "returnOrderDesc": "",
            "principal": "0000100762",
            "bapiSalesDocNumber": "0060153327",
            "eZRxNumber": "EZRX-3a79778",
            "bapiStatus": "SUCCESS",
            "cnNumber": "-",
            "status": "PENDING",
            "statusReason": "-",
            "priceOverride": "",
            "remarks": "",
            "sendForDestruction": false,
            "returnToStock": false,
            "quarantine": false,
            "productRecall": false,
            "returnType": "500",
            "returnTypeDesc": "Return",
            "purchaseNumberCOverride": "",
            "purchaseNumberC": "SG_CART_NO_118",
            "ppaHeld": true,
            "outsidePolicy": false,
            "__typename": "requestInformationV2"
          }
        ],
        "__typename": "requestInformationResponseV2"
      }
    }
  }